loopgrpc/__init__.py
loopgrpc/client.py
loopgrpc/common.py
loopgrpc/compiled/client.proto
loopgrpc/compiled/client_pb2.py
loopgrpc/compiled/client_pb2_grpc.py
loopgrpc/compiled/common.proto
loopgrpc/compiled/common_pb2.py
loopgrpc/compiled/common_pb2_grpc.py
loopgrpc/compiled/debug.proto
loopgrpc/compiled/debug_pb2.py
loopgrpc/compiled/debug_pb2_grpc.py
loopgrpc/compiled/server.proto
loopgrpc/compiled/server_pb2.py
loopgrpc/compiled/server_pb2_grpc.py
loopgrpc/debug.py
loopgrpc/errors.py
loopgrpc/swapclient.py
loop_grpc_client-0.1.3.dist-info/entry_points.txt
loop_grpc_client-0.1.3.dist-info/WHEEL
loop_grpc_client-0.1.3.dist-info/METADATA
loop_grpc_client-0.1.3.dist-info/RECORD
