Metadata-Version: 2.1
Name: loop-grpc-client
Version: 0.1.3
Summary: An rpc client for LL Loop (Add/Remove liquidity from channels)
License: MIT
Author: Kornpow
Author-email: test@email.com
Requires-Python: >3.6
Classifier: License :: OSI Approved :: MIT License
Classifier: Programming Language :: Python :: 3
Classifier: Programming Language :: Python :: 3.7
Classifier: Programming Language :: Python :: 3.8
Classifier: Programming Language :: Python :: 3.9
Requires-Dist: aiogrpc (>=1.8,<2.0)
Requires-Dist: googleapis-common-protos (>=1.53.0,<2.0.0)
Requires-Dist: grpcio (>=1.37.0,<2.0.0)
Requires-Dist: grpcio-tools (>=1.37.0,<2.0.0)
Requires-Dist: protobuf (>=3.15.8,<4.0.0)
Requires-Dist: protobuf3-to-dict (>=0.1.5,<0.2.0)
